minican/CAN.py
minican/__init__.py
minican/broadcastmanager.py
minican/bus.py
minican/canlib.py
minican/ctypesutil.py
minican/interface.py
minican/listener.py
minican/logger.py
minican/message.py
minican/notifier.py
minican/player.py
minican/thread_safe_bus.py
minican/util.py
minican/viewer.py
minican/interfaces/__init__.py
minican/interfaces/canalystii.py
minican/interfaces/iscan.py
minican/interfaces/nican.py
minican/interfaces/slcan.py
minican/interfaces/virtual.py
minican/interfaces/bmcan/__init__.py
minican/interfaces/bmcan/bmapi.py
minican/interfaces/bmcan/canlib.py
minican/interfaces/bmcan/exceptions.py
minican/interfaces/ics_neovi/__init__.py
minican/interfaces/ics_neovi/neovi_bus.py
minican/interfaces/ixxat/__init__.py
minican/interfaces/ixxat/canlib.py
minican/interfaces/ixxat/constants.py
minican/interfaces/ixxat/exceptions.py
minican/interfaces/ixxat/structures.py
minican/interfaces/kvaser/__init__.py
minican/interfaces/kvaser/canlib.py
minican/interfaces/kvaser/constants.py
minican/interfaces/kvaser/structures.py
minican/interfaces/pcan/__init__.py
minican/interfaces/pcan/basic.py
minican/interfaces/pcan/pcan.py
minican/interfaces/serial/__init__.py
minican/interfaces/serial/serial_can.py
minican/interfaces/socketcan/__init__.py
minican/interfaces/socketcan/constants.py
minican/interfaces/socketcan/socketcan.py
minican/interfaces/socketcan/utils.py
minican/interfaces/systec/__init__.py
minican/interfaces/systec/constants.py
minican/interfaces/systec/exceptions.py
minican/interfaces/systec/structures.py
minican/interfaces/systec/ucan.py
minican/interfaces/systec/ucanbus.py
minican/interfaces/usb2can/__init__.py
minican/interfaces/usb2can/serial_selector.py
minican/interfaces/usb2can/usb2canInterface.py
minican/interfaces/usb2can/usb2canabstractionlayer.py
minican/interfaces/vector/__init__.py
minican/interfaces/vector/canlib.py
minican/interfaces/vector/exceptions.py
minican/interfaces/vector/vxlapi.py
minican/io/__init__.py
minican/io/asc.py
minican-0.0.1.dist-info/METADATA
minican-0.0.1.dist-info/WHEEL
minican-0.0.1.dist-info/top_level.txt
minican-0.0.1.dist-info/RECORD
