Metadata-Version: 2.1
Name: minican
Version: 0.0.1
Summary: Minieye Python-CAN
Author-email: Wu Hualong <wuhualong@minieye.cc>
Project-URL: homepage, https://git.minieye.tech/automation/minican
Project-URL: repository, https://git.minieye.tech/automation/minican
Classifier: Programming Language :: Python :: 3
Classifier: License :: OSI Approved :: MIT License
Classifier: Operating System :: OS Independent
Requires-Python: >=3.7
Requires-Dist: aenum (~=3.1.15)
